{
	"$schema": "http://json-schema.org/draft-07/schema#", 
	"$id": "https://github.com/iSPIRT/lsp-lender-protocol-specification/blob/master/Core/schema/Version%200.0.1/dispute.json",  
	"type": "object",
	"required": [
		
	],
	"properties": {
		"id": {
			"type": "string"
		},
		"description": {
			"type": "string"
		},
		"url": { 
			"type": "string"
		},
		"status": { 
			"type": "string",
			"enum": [
				"NEW","PROCESSING","NEED_MORE_INFO","RESOLVED","CLOSED"
			]
		},
		"extensibleData":{
			"$ref": "https://github.com/iSPIRT/lsp-lender-protocol-specification/blob/master/Core/schema/Version%200.0.1/extensibleData.json"
		}
	}
}
